nextcloudtasks/__init__.py
nextcloudtasks/nextcloudtasks.py
nextcloudtasks-0.1.0.data/scripts/nc-tasks.py
nextcloudtasks-0.1.0.dist-info/LICENSE
nextcloudtasks-0.1.0.dist-info/METADATA
nextcloudtasks-0.1.0.dist-info/WHEEL
nextcloudtasks-0.1.0.dist-info/top_level.txt
nextcloudtasks-0.1.0.dist-info/RECORD
