Metadata-Version: 2.1
Name: nextcloudtasks
Version: 0.1.0
Summary: A Nextcloud Tasks API wrapper with some useful examples for CLI
Home-page: https://github.com/sinkmanu/nextcloud-tasks
Author: Manuel Mancera
Author-email: Manuel Mancera <manu@unam.re>
License: GPL-3.0-or-later
Project-URL: Homepage, https://github.com/sinkmanu/nextcloud-tasks
Project-URL: Source, https://github.com/sinkmanu/nextcloud-tasks
Project-URL: Bug Tracker, https://github.com/sinkmanu/nextcloud-tasks/issues
Keywords: nextcloud,todo,nextcloud tasks
Classifier: Programming Language :: Python :: 3
Classifier: License :: OSI Approved :: GNU General Public License v3 or later (GPLv3+)
Classifier: Operating System :: OS Independent
Requires-Python: >=3.6
License-File: LICENSE
Requires-Dist: caldav
Requires-Dist: prettytable
